MANIFEST.in
README.txt
requirements.txt
setup.py
agua/__init__.py
agua/comparators.py
agua/config.py
agua/evaluate.py
agua/termgraph.py
agua/utils.py
agua/validators.py
agua.egg-info/PKG-INFO
agua.egg-info/SOURCES.txt
agua.egg-info/dependency_links.txt
agua.egg-info/entry_points.txt
agua.egg-info/requires.txt
agua.egg-info/top_level.txt