Metadata-Version: 1.1
Name: agua
Version: 0.1.1
Summary: Compare data in columns with other columns with the help of comparator functions
Home-page: https://github.com/CompileInc/agua
Author: UNKNOWN
Author-email: UNKNOWN
License: MIT
Download-URL: https://github.com/CompileInc/agua/archive/v0.1.1.tar.gz
Keywords: agua,testing,data,csv
Platform: UNKNOWN
